objectionloltotxt/__init__.py
objectionloltotxt/__main__.py
objectionloltotxt/objectiontotxt.py
objectionloltotxt-0.4.1.dist-info/LICENSE
objectionloltotxt-0.4.1.dist-info/METADATA
objectionloltotxt-0.4.1.dist-info/WHEEL
objectionloltotxt-0.4.1.dist-info/entry_points.txt
objectionloltotxt-0.4.1.dist-info/top_level.txt
objectionloltotxt-0.4.1.dist-info/RECORD
