Metadata-Version: 2.1
Name: objectionloltotxt
Version: 0.4.1
Summary: Converts .objection files to readable Txt
Home-page: https://github.com/Erdal-oz/objectiontotxt
Author: Plright
Author-email: plright1@protonmail.com
License: UNKNOWN
Project-URL: Bug Tracker, https://github.com/Erdal-oz/objectiontotxt/issues
Platform: UNKNOWN
Classifier: Programming Language :: Python :: 3
Classifier: License :: OSI Approved :: The Unlicense (Unlicense)
Classifier: Operating System :: OS Independent
Requires-Python: >=3.6
License-File: LICENSE
